{
    "headline": "TV Malaysia Live",
    "menu": [
        {
            "icon": "tv",
            "label": "TV1",
            "data": {
                "type": "pages",
                "items": [
                    {
                        "title": "TV1",
                        "action": "link:https://www.tvmalaysia.live/channel/tv1"
                    }
                ]
            }
        },
        {
            "icon": "tv",
            "label": "TV2",
            "data": {
                "type": "pages",
                "items": [
                    {
                        "title": "TV2",
                        "action": "link:https://www.tvmalaysia.live/channel/tv2"
                    }
                ]
            }
        },
        {
            "icon": "tv",
            "label": "TV3",
            "data": {
                "type": "pages",
                "items": [
                    {
                        "title": "TV3",
                        "action": "link:https://www.tvmalaysia.live/channel/tv3live"
                    }
                ]
            }
        }
    ]
}
